pysiemens/__init__.py
pysiemens/address_patterns.py
pysiemens/errors.py
pysiemens/s7_parser.py
pysiemens/s7_plc.py
pysiemens/utils.py
pysiemens/schemas/__init__.py
pysiemens/schemas/memory_areas.py
pysiemens/schemas/primitive.py
pysiemens/schemas/s7_data_schema.py
pysiemens/schemas/s7_plc_schema.py
pysiemens_s7-0.0.3.dist-info/LICENSE
pysiemens_s7-0.0.3.dist-info/METADATA
pysiemens_s7-0.0.3.dist-info/WHEEL
pysiemens_s7-0.0.3.dist-info/entry_points.txt
pysiemens_s7-0.0.3.dist-info/top_level.txt
pysiemens_s7-0.0.3.dist-info/RECORD
