Metadata-Version: 2.1
Name: pysiemens-s7
Version: 0.0.3
Summary: Address and data parsing for python-snap7 package
Author-email: Josep Ma Pujades <jmpujades.dev@proton.me>
License: MIT
Project-URL: Homepage, https://github.com/freeconversation/pysiemens-s7
Project-URL: Bug Reports, https://github.com/freeconversation/pysiemens-s7/issues
Classifier: Environment :: Console
Classifier: Topic :: System :: Hardware
Classifier: Intended Audience :: Developers
Classifier: Intended Audience :: Manufacturing
Classifier: License :: OSI Approved :: MIT License
Classifier: Operating System :: POSIX
Classifier: Programming Language :: Python :: 3.9
Classifier: Programming Language :: Python :: 3.10
Classifier: Programming Language :: Python :: 3.11
Requires-Python: >=3.9
License-File: LICENSE
Requires-Dist: annotated-types >=0.5.0
Requires-Dist: iniconfig >=2.0.0
Requires-Dist: packaging >=23.1
Requires-Dist: pluggy >=1.3.0
Requires-Dist: pydantic >=2.3.0
Requires-Dist: pydantic-core >=2.6.3
Requires-Dist: pytest >=7.4.2
Requires-Dist: python-snap7 >=1.3
Requires-Dist: typing-extensions >=4.8.0
Provides-Extra: test
Requires-Dist: pytest ; extra == 'test'
Requires-Dist: pytest-asyncio ; extra == 'test'
Requires-Dist: mypy ; extra == 'test'
Requires-Dist: pycodestyle ; extra == 'test'
Requires-Dist: types-setuptools ; extra == 'test'
